pybpjs/__init__.py
pybpjs/bpjs.py
pybpjs-0.0.5.dist-info/LICENSE
pybpjs-0.0.5.dist-info/METADATA
pybpjs-0.0.5.dist-info/WHEEL
pybpjs-0.0.5.dist-info/top_level.txt
pybpjs-0.0.5.dist-info/RECORD
