Metadata-Version: 2.1
Name: pybpjs
Version: 0.0.5
Summary: Aplikasi Python yang digunakan untuk menangani proses dekripsi respon data dari bridging BPJS VClaim v2.0 (Encrypted Version). Support VClaim v1 / v1.1 dan Antrean RS.
Home-page: https://github.com/morizbebenk/pybpjs
Author: Moriz
Author-email: morizbebenk@gmail.com
License: MIT
Project-URL: Bug Tracker, https://github.com/morizbebenk/pybpjs/issues
Keywords: bpjs vclaim vclaim-rest vclaim-encrypted
Platform: UNKNOWN
Classifier: Operating System :: OS Independent
Classifier: License :: OSI Approved :: MIT License
Classifier: Programming Language :: Python :: 3.5
Classifier: Programming Language :: Python :: 3.6
Classifier: Programming Language :: Python :: 3.7
Classifier: Programming Language :: Python :: 3.8
Classifier: Programming Language :: Python :: 3.9
Classifier: Programming Language :: Python :: 3.10
Requires-Python: >=3.6
License-File: LICENSE
Requires-Dist: lzstring
Requires-Dist: requests
Requires-Dist: pycryptodome
